aliyunsdkeflo/__init__.py
aliyunsdkeflo/request/__init__.py
aliyunsdkeflo/request/v20220530/AssignLeniPrivateIpAddressRequest.py
aliyunsdkeflo/request/v20220530/AssignPrivateIpAddressRequest.py
aliyunsdkeflo/request/v20220530/AssociateVpdCidrBlockRequest.py
aliyunsdkeflo/request/v20220530/CreateElasticNetworkInterfaceRequest.py
aliyunsdkeflo/request/v20220530/CreateErAttachmentRequest.py
aliyunsdkeflo/request/v20220530/CreateErRequest.py
aliyunsdkeflo/request/v20220530/CreateErRouteMapRequest.py
aliyunsdkeflo/request/v20220530/CreateSubnetRequest.py
aliyunsdkeflo/request/v20220530/CreateVccGrantRuleRequest.py
aliyunsdkeflo/request/v20220530/CreateVccRequest.py
aliyunsdkeflo/request/v20220530/CreateVccRouteEntryRequest.py
aliyunsdkeflo/request/v20220530/CreateVpdGrantRuleRequest.py
aliyunsdkeflo/request/v20220530/CreateVpdRequest.py
aliyunsdkeflo/request/v20220530/DeleteElasticNetworkInterfaceRequest.py
aliyunsdkeflo/request/v20220530/DeleteErAttachmentRequest.py
aliyunsdkeflo/request/v20220530/DeleteErRequest.py
aliyunsdkeflo/request/v20220530/DeleteErRouteMapRequest.py
aliyunsdkeflo/request/v20220530/DeleteSubnetRequest.py
aliyunsdkeflo/request/v20220530/DeleteVccGrantRuleRequest.py
aliyunsdkeflo/request/v20220530/DeleteVccRouteEntryRequest.py
aliyunsdkeflo/request/v20220530/DeleteVpdGrantRuleRequest.py
aliyunsdkeflo/request/v20220530/DeleteVpdRequest.py
aliyunsdkeflo/request/v20220530/DescribeSlrRequest.py
aliyunsdkeflo/request/v20220530/GetElasticNetworkInterfaceRequest.py
aliyunsdkeflo/request/v20220530/GetErAttachmentRequest.py
aliyunsdkeflo/request/v20220530/GetErRequest.py
aliyunsdkeflo/request/v20220530/GetErRouteEntryRequest.py
aliyunsdkeflo/request/v20220530/GetErRouteMapRequest.py
aliyunsdkeflo/request/v20220530/GetFabricTopologyRequest.py
aliyunsdkeflo/request/v20220530/GetLeniPrivateIpAddressRequest.py
aliyunsdkeflo/request/v20220530/GetLniPrivateIpAddressRequest.py
aliyunsdkeflo/request/v20220530/GetNetworkInterfaceRequest.py
aliyun_python_sdk_eflo-1.0.18.dist-info/LICENSE
aliyun_python_sdk_eflo-1.0.18.dist-info/METADATA
aliyun_python_sdk_eflo-1.0.18.dist-info/WHEEL
aliyun_python_sdk_eflo-1.0.18.dist-info/top_level.txt
aliyun_python_sdk_eflo-1.0.18.dist-info/RECORD
